EzMetrics
