Metadata-Version: 2.1
Name: EzMetrics
Version: 1.0
Summary: An easy package to use for to get metrics from your models
Home-page: https://github.com/JieWuu/EzMetrics
Download-URL: https://github.com/JieWuu/EzMetrics/archive/refs/tags/v_1.0.tar.gz
Author: Jie Wu, Asier Marinero
Author-email: jie.wu@alumni.mondragon.edu, asier.marinero@alumni.mondragon.edu
License: MIT
Keywords: Easy,Metrics,Model
Classifier: Development Status :: 3 - Alpha
Classifier: Intended Audience :: Developers
Classifier: Topic :: Software Development :: Build Tools
Classifier: License :: OSI Approved :: MIT License
Classifier: Programming Language :: Python :: 3
Classifier: Programming Language :: Python :: 3.7
Classifier: Programming Language :: Python :: 3.8
Classifier: Programming Language :: Python :: 3.9
Classifier: Programming Language :: Python :: 3.10
License-File: LICENSE.txt
